{
  "project_info": {
    "project_number": "534301846445",
    "project_id": "accessible-shop",
    "storage_bucket": "accessible-shop.firebasestorage.app"
  },
  "client": [
    {
      "client_info": {
        "mobilesdk_app_id": "1:534301846445:android:d586179866a76b2d56cf24",
        "android_client_info": {
          "package_name": "com.example.accessible_shop"
        }
      },
      "oauth_client": [],
      "api_key": [
        {
          "current_key": "AIzaSyC5kyO71JsBjAnJkh_KZsGhBZwpRkE3vos"
        }
      ],
      "services": {
        "appinvite_service": {
          "other_platform_oauth_client": []
        }
      }
    }
  ],
  "configuration_version": "1"
}